{
  "main": {
    "id": "6d88250d03e1278c",
    "type": "split",
    "children": [
      {
        "id": "ecd9e8f1b944ac96",
        "type": "tabs",
        "children": [
          {
            "id": "0994f1f99350f624",
            "type": "leaf",
            "state": {
              "type": "markdown",
              "state": {
                "file": "Docker/Network.md",
                "mode": "source",
                "source": false
              }
            }
          },
          {
            "id": "ee949733654c7bcf",
            "type": "leaf",
            "state": {
              "type": "markdown",
              "state": {
                "file": "PostgreSQL/Подключение DB к коду.md",
                "mode": "source",
                "source": false
              }
            }
          },
          {
            "id": "a210ffaa2ffdb17b",
            "type": "leaf",
            "state": {
              "type": "markdown",
              "state": {
                "file": "Docker/Команды.md",
                "mode": "source",
                "source": false
              }
            }
          },
          {
            "id": "ddf7b9f996c64154",
            "type": "leaf",
            "state": {
              "type": "markdown",
              "state": {
                "file": "Docker/Синхронизация файлов.md",
                "mode": "source",
                "source": false
              }
            }
          },
          {
            "id": "8124f758c3a45369",
            "type": "leaf",
            "state": {
              "type": "markdown",
              "state": {
                "file": "PostgreSQL/Консольные команды.md",
                "mode": "source",
                "source": false
              }
            }
          },
          {
            "id": "2dad82561c949bd8",
            "type": "leaf",
            "state": {
              "type": "markdown",
              "state": {
                "file": "PostgreSQL/Команды.md",
                "mode": "source",
                "source": false
              }
            }
          }
        ],
        "currentTab": 2
      }
    ],
    "direction": "vertical"
  },
  "left": {
    "id": "818f46c4ae586588",
    "type": "split",
    "children": [
      {
        "id": "c1b826a5cb1f3987",
        "type": "tabs",
        "children": [
          {
            "id": "2b60069b0cfcde76",
            "type": "leaf",
            "state": {
              "type": "file-explorer",
              "state": {
                "sortOrder": "alphabetical"
              }
            }
          },
          {
            "id": "3912707e8b506022",
            "type": "leaf",
            "state": {
              "type": "search",
              "state": {
                "query": "",
                "matchingCase": false,
                "explainSearch": false,
                "collapseAll": false,
                "extraContext": false,
                "sortOrder": "alphabetical"
              }
            }
          },
          {
            "id": "83d07de4920b2307",
            "type": "leaf",
            "state": {
              "type": "bookmarks",
              "state": {}
            }
          }
        ]
      }
    ],
    "direction": "horizontal",
    "width": 200
  },
  "right": {
    "id": "8ed63cac4e77dcc9",
    "type": "split",
    "children": [
      {
        "id": "b12cf36d51660eb5",
        "type": "tabs",
        "children": [
          {
            "id": "5d5f92a83a9f9a2e",
            "type": "leaf",
            "state": {
              "type": "backlink",
              "state": {
                "file": "Docker/Команды.md",
                "collapseAll": true,
                "extraContext": false,
                "sortOrder": "alphabetical",
                "showSearch": false,
                "searchQuery": "",
                "backlinkCollapsed": false,
                "unlinkedCollapsed": true
              }
            }
          },
          {
            "id": "5240032f3492e81f",
            "type": "leaf",
            "state": {
              "type": "outgoing-link",
              "state": {
                "file": "Docker/Команды.md",
                "linksCollapsed": false,
                "unlinkedCollapsed": true
              }
            }
          },
          {
            "id": "2ad6a939a3efdea7",
            "type": "leaf",
            "state": {
              "type": "tag",
              "state": {
                "sortOrder": "frequency",
                "useHierarchy": true
              }
            }
          },
          {
            "id": "cfcdef0372395f6f",
            "type": "leaf",
            "state": {
              "type": "outline",
              "state": {
                "file": "Docker/Команды.md"
              }
            }
          },
          {
            "id": "3ef0b22fe4d69e67",
            "type": "leaf",
            "state": {
              "type": "advanced-tables-toolbar",
              "state": {}
            }
          }
        ],
        "currentTab": 3
      }
    ],
    "direction": "horizontal",
    "width": 300
  },
  "left-ribbon": {
    "hiddenItems": {
      "switcher:Меню быстрого перехода": false,
      "graph:Граф": false,
      "canvas:Создать новый холст": false,
      "templates:Вставить шаблон": false,
      "command-palette:Открыть палитру команд": false
    }
  },
  "active": "a210ffaa2ffdb17b",
  "lastOpenFiles": [
    "Docker/Синхронизация файлов.md",
    "Docker/Команды.md",
    "PostgreSQL/Команды.md",
    "PostgreSQL/Подключение DB к коду.md",
    "PostgreSQL/Консольные команды.md",
    "Docker/Network.md",
    "PostgreSQL/Установка.md",
    "Docker/Установка.md",
    "Docker/Data/Pasted image 20240115121016.png",
    "Docker/Data/Pasted image 20240115120915.png",
    "Docker/Dockerfile.md",
    "Docker/Разное.md",
    "Linux/Консольные команды.md",
    "Python/ENV.md",
    "Python/Pip.md",
    "Git/Основные команды.md",
    "Git/Начало работы с новым проектом.md",
    "Git/Настройка git.md",
    "Python/Разное.md",
    "Python/Fluent.md",
    "Python/Библиотеки Python.md",
    "Python/Tabulate.md",
    "Python/Selenium.md",
    "Linux/Obsidian.md",
    "Linux/Установка расширений.md",
    "Python/PostgreSQL.md",
    "PostgreSQL/pgAdmin 4/Установка.md",
    "PostgreSQL/pgAdmin 4",
    "PostgreSQL",
    "Python/Logs.md",
    "Python/Без названия",
    "Pasted image 20231204150719.png",
    "Deutsch/Репет/Pasted image 20240105161733.png",
    "Deutsch/Репет/Pasted image 20240105160238.png",
    "Deutsch/Репет/Pasted image 20240105153808.png",
    "Deutsch/Репет/Pasted image 20240105013413.png",
    "Deutsch/Репет/Pasted image 20240105013024.png",
    "Deutsch/Репет/Pasted image 20240105012149.png",
    "Deutsch/Репет/Pasted image 20240103150838.png",
    "Deutsch/Репет/Файлы",
    "Deutsch/Репет",
    "Телеграм бот хелпер для уника",
    "Deutsch",
    "Python/Aiogram",
    "templates",
    "Без названия.canvas",
    "Raspberry",
    "Untitled.canvas"
  ]
}